kmsgrid.py
kmsgrid-1.1.0.dist-info/DESCRIPTION.rst
kmsgrid-1.1.0.dist-info/METADATA
kmsgrid-1.1.0.dist-info/RECORD
kmsgrid-1.1.0.dist-info/WHEEL
kmsgrid-1.1.0.dist-info/entry_points.txt
kmsgrid-1.1.0.dist-info/metadata.json
kmsgrid-1.1.0.dist-info/top_level.txt
