Metadata-Version: 2.0
Name: kmsgrid
Version: 1.1.0
Summary: Read and convert grids from KMS.
Home-page: https://github.com/Kortforsyningen/kmsgrid
Author: Kristian Evers
Author-email: kreve@sdfe.dk
License: ISC
Keywords: kms geodesy grids geoid datumshift gridshift
Platform: UNKNOWN
Classifier: Development Status :: 5 - Production/Stable
Classifier: Intended Audience :: Developers
Classifier: Intended Audience :: Science/Research
Classifier: License :: OSI Approved :: ISC License (ISCL)
Classifier: Topic :: Scientific/Engineering :: GIS
Classifier: Topic :: Utilities
Requires-Dist: numpy
Requires-Dist: gdal
